jarvis/__init__.py
jarvis/ai/__init__.py
jarvis/ai/descriptors/__init__.py
jarvis/ai/descriptors/cfid.py
jarvis/ai/descriptors/coulomb.py
jarvis/ai/descriptors/elemental.py
jarvis/ai/gcn/__init__.py
jarvis/ai/pkgs/__init__.py
jarvis/ai/pkgs/utils.py
jarvis/ai/pkgs/lgbm/__init__.py
jarvis/ai/pkgs/lgbm/classification.py
jarvis/ai/pkgs/lgbm/regression.py
jarvis/ai/pkgs/sklearn/__init__.py
jarvis/ai/pkgs/sklearn/classification.py
jarvis/ai/pkgs/sklearn/hyper_params.py
jarvis/ai/pkgs/sklearn/regression.py
jarvis/ai/uncertainty/__init__.py
jarvis/ai/uncertainty/gaussian_process_uncertainty.py
jarvis/ai/uncertainty/lgbm_quantile_uncertainty.py
jarvis/analysis/__init__.py
jarvis/analysis/darkmatter/__init__.py
jarvis/analysis/darkmatter/metrics.py
jarvis/analysis/defects/__init__.py
jarvis/analysis/defects/substitutions.py
jarvis/analysis/defects/surface.py
jarvis/analysis/defects/vacancy.py
jarvis/analysis/diffraction/__init__.py
jarvis/analysis/diffraction/atomic_scattering_params.json
jarvis/analysis/diffraction/xrd.py
jarvis/analysis/elastic/__init__.py
jarvis/analysis/elastic/tensor.py
jarvis/analysis/interface/__init__.py
jarvis/analysis/interface/zur.py
jarvis/analysis/magnetism/__init__.py
jarvis/analysis/magnetism/magmom_setup.py
jarvis/analysis/periodic/__init__.py
jarvis/analysis/periodic/ptable.py
jarvis/analysis/phonon/__init__.py
jarvis/analysis/phonon/dos.py
jarvis/analysis/phonon/force_constants.py
jarvis/analysis/phonon/ir.py
jarvis/analysis/solarefficiency/__init__.py
jarvis/analysis/solarefficiency/am1.5G.dat
jarvis/analysis/solarefficiency/solar.py
jarvis/analysis/stem/__init__.py
jarvis/analysis/stem/convolution_apprx.py
jarvis/analysis/stm/__init__.py
jarvis/analysis/stm/tersoff_hamann.py
jarvis/analysis/structure/__init__.py
jarvis/analysis/structure/neighbors.py
jarvis/analysis/structure/spacegroup.py
jarvis/analysis/thermodynamics/__init__.py
jarvis/analysis/thermodynamics/energetics.py
jarvis/analysis/thermodynamics/unary.json
jarvis_tools-2025.5.30.dist-info/METADATA
jarvis_tools-2025.5.30.dist-info/WHEEL
jarvis_tools-2025.5.30.dist-info/top_level.txt
jarvis_tools-2025.5.30.dist-info/RECORD
