Metadata-Version: 2.2
Name: jarvis-tools
Version: 2025.5.30
Summary: jarvis-tools: an open-source software package for data-driven atomistic materials design. https://jarvis.nist.gov/
Home-page: https://github.com/atomgptlab/jarvis-tools
Author: Kamal Choudhary
Author-email: kamal.choudhary@nist.gov
License: MIT
Classifier: Programming Language :: Python :: 3.6
Classifier: Development Status :: 4 - Beta
Classifier: Intended Audience :: Science/Research
Classifier: Operating System :: OS Independent
Classifier: Topic :: Scientific/Engineering
Requires-Dist: numpy>=1.20.1
Requires-Dist: scipy>=1.5.0
Requires-Dist: matplotlib>=3.0.0
Requires-Dist: joblib>=0.14.1
Requires-Dist: requests>=2.23.0
Requires-Dist: toolz>=0.9.0
Requires-Dist: xmltodict>=0.11.0
Requires-Dist: tqdm>=4.41.1
Requires-Dist: scikit-learn
Provides-Extra: doc
Requires-Dist: sphinx>=1.3.1; extra == "doc"
Requires-Dist: sphinx-rtd-theme>=0.1.8; extra == "doc"
Dynamic: author
Dynamic: author-email
Dynamic: classifier
Dynamic: description
Dynamic: home-page
Dynamic: license
Dynamic: provides-extra
Dynamic: requires-dist
Dynamic: summary
